veeam_exporter/__init__.py
veeam_exporter/build_conf.py
veeam_exporter/collector.py
veeam_exporter/constants.py
veeam_exporter/core_exporter.py
veeam_exporter/filters.py
veeam_exporter/veeam_api.py
veeam_exporter/veeam_exporter.py
veeam_exporter/yamlscript.py
veeam_exporter/conf/config.yml
veeam_exporter/conf/metrics/backup_agent_metrics.yml
veeam_exporter/conf/metrics/backup_jobs_sessions_metrics.yml
veeam_exporter/conf/metrics/backup_servers_metrics.yml
veeam_exporter/conf/metrics/jobs_overview_metrics.yml
veeam_exporter/conf/metrics/repositories_metrics.yml
veeam_exporter/conf/metrics/veeam_overview_metrics.yml
veeam_exporter/conf/metrics/vm_backup_jobs_sessions_metrics.yml
veeam_exporter/conf/metrics/vm_overview_metrics.yml
veeam_exporter/custom_filters/__init__.py
veeam_exporter/custom_filters/agent_status.py
veeam_exporter/custom_filters/backup_server.py
veeam_exporter/custom_filters/defaults.py
veeam_exporter/custom_filters/hashsum.py
veeam_exporter/custom_filters/job_status.py
veeam_exporter/custom_filters/to_timestamp.py
veeam_exporter/custom_filters/vmjob_status.py
veeam_exporter-1.1.0.dist-info/LICENSE
veeam_exporter-1.1.0.dist-info/METADATA
veeam_exporter-1.1.0.dist-info/WHEEL
veeam_exporter-1.1.0.dist-info/entry_points.txt
veeam_exporter-1.1.0.dist-info/top_level.txt
veeam_exporter-1.1.0.dist-info/RECORD
