Metadata-Version: 2.1
Name: veeam-exporter
Version: 1.1.0
Summary: A Python-based Veeam Entreprise Exporter for Prometheus
Home-page: https://github.com/peekjef72/veeam_exporter
Author: peekjef72
Author-email: jfpik78@gmail.com
License-File: LICENSE
Requires-Dist: prometheus-client (>=0.8.0)
Requires-Dist: requests (==2.23.0)
Requires-Dist: PyYAML (==5.3.1)
Requires-Dist: tenacity (==6.2.0)
Requires-Dist: urllib3 (>=1.25.9)
Requires-Dist: Jinja2 (>=2.11.2)
Requires-Dist: python-dateutil (>=0.6.12)
